fracture_suite/__init__.py
fracture_suite/analyzer.py
fracture_suite/preprocess.py
fracture_suite/splinter.py
fracture_suite-0.0.2.dist-info/METADATA
fracture_suite-0.0.2.dist-info/WHEEL
fracture_suite-0.0.2.dist-info/top_level.txt
fracture_suite-0.0.2.dist-info/RECORD
