Metadata-Version: 2.1
Name: fracture-suite
Version: 0.0.2
Summary: Package to help analyze fracture patterns on broken glass plys.
Author-email: Leon Bohmann <mail@leonbohmann.de>
Project-URL: Homepage, https://github.com/leonbohmann/fracture-suite
Project-URL: Bug Tracker, https://github.com/leonbohmann/fracture-suite/issues
Classifier: Programming Language :: Python :: 3
Classifier: License :: OSI Approved :: MIT License
Classifier: Operating System :: OS Independent
Requires-Python: >=3.7
Requires-Dist: matplotlib
Requires-Dist: opencv-python
Requires-Dist: numpy
Requires-Dist: tqdm
Requires-Dist: scikit-image
